dekegg-0.1.12.dist-info/METADATA
dekegg-0.1.12.dist-info/WHEEL
dekegg-0.1.12.dist-info/entry_points.txt
dekegg/__init__.py
dekegg/bdist/__init__.py
dekegg/bdist/fixegg.py
dekegg/bdist/fullegg.py
dekegg/core.py
dekegg/templatefiles/project/pyproject.toml-tpl
dekegg/tmpl.py
dekegg-0.1.12.dist-info/RECORD
