Metadata-Version: 2.1
Name: dekegg
Version: 0.1.12
Author-Email: sanzenwin <sanzenwin@gmail.com>
License: MIT
Requires-Python: >=3.10
Requires-Dist: setuptools
Requires-Dist: dektools[ignore]<1.0.0
Requires-Dist: dekgen<1.0.0
